setup.py
twitter_crawler/__init__.py
twitter_crawler/api.py
twitter_crawler/error.py
twitter_crawler.egg-info/PKG-INFO
twitter_crawler.egg-info/SOURCES.txt
twitter_crawler.egg-info/dependency_links.txt
twitter_crawler.egg-info/requires.txt
twitter_crawler.egg-info/top_level.txt