Metadata-Version: 2.1
Name: twitter-crawler
Version: 1.6
Summary: An Twitter scraping tool without account
Home-page: UNKNOWN
Author: 潘闯界
Author-email: is_chuangjie@163.com
License: UNKNOWN
Platform: UNKNOWN
Classifier: Programming Language :: Python :: 3
Classifier: License :: OSI Approved :: MIT License
Classifier: Operating System :: OS Independent
Requires-Python: >=3.6
